{
  "cities": [
    {
      "name": "南京",
      "province": "江苏",
      "fans": [
        {
          "id": "wish-01",
          "name": "归辞辞呀",
          "icon": "💌",
          "location": "江苏/南京",
          "message": "主包生日快乐~要每天开开心心健健康康的呀(=^▽^=)",
          "avatar": "",
          "audio": "audio/wish-01.m4a"
        }
      ]
    },
    {
      "name": "海口",
      "province": "海南",
      "fans": [
        {
          "id": "wish-03",
          "name": "光砸",
          "icon": "🌺",
          "location": "海南/海口",
          "message": "祝大哥年年岁岁平安喜乐，岁岁年年风采依旧，永远青春，永远热泪盈眶，永远少年！一路繁花，直播长红！（如果还是攒不住财，可以放我这，我帮您存着，哈哈哈哈。）",
          "avatar": "",
          "audio": "audio/wish-03.mp3"
        }
      ]
    },
    {
      "name": "沈阳",
      "province": "辽宁",
      "fans": [
        {
          "id": "wish-04",
          "name": "么么",
          "icon": "🤍",
          "location": "辽宁/沈阳",
          "message": "此时无声胜有声，省略十万句",
          "avatar": "",
          "audio": "audio/wish-04.m4a"
        }
      ]
    },
        {
          "id": "wish-15",
          "name": "晴琴",
          "icon": "🎵",
          "location": "台湾",
          "message": "谜屿~爷爷呀~生日快乐~祝你每天都健康平安~喜乐常在~抽抽都白到发光呀~谢谢你每天的陪伴~从刚进猫耳就遇见你到现在~真的是非常的幸运呀~很开心能够来到你的直播间和大家相遇~一听到你唱歌心情都变好了~待着真的很放松~很喜欢待在这里~就是这样！ 爷爷生日快乐呀~天天开心！！！",
          "avatar": "",
          "audio": "audio/wish-15.m4a"
        }
      ]
    },
    {
      "name": "深圳",
      "province": "广东",
      "fans": [
        {
          "id": "wish-06",
          "name": "小韦",
          "icon": "🎙️",
          "location": "广东/深圳",
          "message": "",
          "avatar": "",
          "audio": "audio/wish-06.m4a"
        }
      ]
    },
    {
      "name": "曲靖",
      "province": "云南",
      "fans": [
        {
          "id": "wish-07",
          "name": "小宝",
          "icon": "🎈",
          "location": "云南/曲靖",
          "message": "生日快乐呀！（由于学校不放假，所以没办法回来，小小原谅一下下我吧）",
          "avatar": "",
          "audio": "audio/wish-07.mp3"
        }
      ]
    },
    {
      "name": "长沙",
      "province": "湖南",
      "fans": [
        {
          "id": "wish-08",
          "name": "谜屿是无花爷爷",
          "icon": "🌙",
          "location": "湖南/长沙",
          "message": "认识时间不算长但也不短了，在你这里我是放松的随意的，今天你生日，愿你平安喜乐，收获更多人偏爱和喜欢，所愿皆所得。生日快乐\"爷爷\"",
          "avatar": "",
          "audio": "audio/wish-08.mp3"
        }
      ]
    },
    {
      "name": "齐齐哈尔",
      "province": "黑龙江",
      "fans": [
        {
          "id": "wish-09",
          "name": "微笑",
          "icon": "😊",
          "location": "黑龙江/齐齐哈尔",
          "message": "生日快乐，身体健康，祝大哥开心顺意，越来越帅气，唱歌越来越好听，小耳朵越来越多，哈哈哈哈哈",
          "avatar": "",
          "audio": "audio/wish-09.mp3"
        }
      ]
    },
{
  "name": "台北",
  "province": "台湾",
  "fans": [
    {
      "id": "wish-05",
      "name": "初心的向陽",
      "icon": "🌻",
      "location": "台湾/台北",
      "message": "生日快樂🎂心願達成🎉平安健康~不再花大錢~錢永遠存住留住在自己身上🥳🥳🥳",
      "avatar": "",
      "audio": "audio/wish-05.mp3"
    },
    {
      "id": "wish-10",
      "name": "布丁",
      "icon": "🐱",
      "location": "台湾/台北",
      "message": "亲爱的大哥，生日快乐呀🎂希望新的一岁，你要好好照顾自己。愿你拥有健康的身体、日常的快乐、热爱的生活，以及始终愿意陪伴你的人。愿你被世界温柔以待，也愿你永远保有最初热爱唱歌的那颗心。🩵",
      "avatar": "",
      "audio": "audio/wish-10.mp3"
    }
  ]
},
{
  "name": "台湾",
  "province": "台湾",
  "fans": [
    {
      "id": "wish-15",
      "name": "晴琴",
      "icon": "🎵",
      "location": "台湾",
      "message": "谜屿~爷爷呀~生日快乐~祝你每天都健康平安~喜乐常在~抽抽都白到发光呀~谢谢你每天的陪伴~从刚进猫耳就遇见你到现在~真的是非常的幸运呀~很开心能够来到你的直播间和大家相遇~一听到你唱歌心情都变好了~待着真的很放松~很喜欢待在这里~就是这样！ 爷爷生日快乐呀~天天开心！！！",
      "avatar": "",
      "audio": "audio/wish-15.m4a"
    }
  ]
},
    {
      "name": "延边",
      "province": "吉林",
      "fans": [
        {
          "id": "wish-11",
          "name": "玄子",
          "icon": "🫶",
          "location": "吉林/延边",
          "message": "哑了就不给你语音祝福了，祝我的命运共同体生日快乐！永远不死（不是）！",
          "avatar": "",
          "audio": "audio/wish-11.mp3"
        }
      ]
    },
    {
      "name": "上海",
      "province": "上海",
      "fans": [
        {
          "id": "wish-12",
          "name": "叮当",
          "icon": "✨",
          "location": "上海",
          "message": "顺遂无虞，皆得所愿",
          "avatar": "",
          "audio": "audio/wish-12.mp3"
        }
      ]
    },
    {
      "name": "张家界",
      "province": "湖南",
      "fans": [
        {
          "id": "wish-13",
          "name": "Eleven_咖啡",
          "icon": "☕",
          "location": "湖南/张家界",
          "message": "生日快乐，今年因为忙现生很少来和大家一起玩，等我空了一定回来，等我嗷！！！！我很期待见到业主群庞大的样子✌🏻",
          "avatar": "",
          "audio": "audio/wish-13.m4a"
        }
      ]
    },
    {
      "name": "湖州",
      "province": "浙江",
      "fans": [
        {
          "id": "wish-14",
          "name": "黑裙独白",
          "icon": "🖤",
          "location": "浙江/湖州",
          "message": "祝福谜屿生日快乐🎉，牙好身体好",
          "avatar": "",
          "audio": "audio/wish-14.mp3"
        }
      ]
    }
  ]
}
